100_days_of_RTL/day_3_rise_fall_edge_dect/rise_fall_edge_dect.sv
// Design and verify a rising and falling edge detector

module rise_fall_edge_dect (
    input wire clk,
    input wire rst,
    input wire a_i,

    output logic out_rise,
    output logic out_fall
); 

logic prev_a_i;

always @(posedge clk or posedge rst)
begin
    if(rst)
    begin
    out_rise <= 1'b0;
    out_fall <= 1'b0;
    prev_a_i <= 1'b0;
    end

    else 
    begin
    out_rise <= (~prev_a_i) & a_i; //for rise edge -> previous value = 0 ,current value -> 1
    out_fall <= prev_a_i & (~a_i); //for fall edge -> previous value = 1 ,current value -> 0
    end
end

always @(posedge clk or posedge rst)
begin
    prev_a_i <= a_i;
end

/*
always @(posedge clk or posedge rst)
begin
    if(rst)
    begin
    //out_rise <= 1'b0;
    //out_fall <= 1'b0;
    prev_a_i <= 1'b0;
    end
    else 
    prev_a_i <= a_i;
end

//assign statements execute in parallel with always block
assign out_rise = (~prev_a_i) & a_i; //for rise edge -> previous value = 0 ,current value -> 1
assign out_fall = prev_a_i & (~a_i); //for fall edge -> previous value = 1 ,current value -> 0

//The prev_a_i signal is updated on the clock edge, 
//and the assign statements continuously monitor the values of prev_a_i and a_i, 
//and the outputs (out_rise and out_fall) are updated whenever these signals change.
*/

endmodule

100_days_of_RTL/day_3_rise_fall_edge_dect/rise_fall_edge_dect_tb.sv
`include "rise_fall_edge_dect.sv"

module rise_fall_edge_dect_tb;

logic clk,rst,a_i,out_rise,out_fall;

rise_fall_edge_dect uut(.*);

initial begin
forever #5 clk=~clk;
end

initial begin
    clk=0;
    rst=1;
    a_i=0;
    #10 rst=0;
    #10 a_i=1;
    #20 a_i=0;
    #10 a_i=1;
     rst=1;
    #10 a_i=0;
    #10 a_i=1;
    #20 a_i=0;
    rst=0;
    #10 a_i=1;
    #10 a_i=0;
    #10 a_i=1;
    #20 a_i=0;
    #10 a_i=1;
    #10 a_i=0;

   #20 $finish;

end

initial begin
    $monitor("time=%t\t clk=%b\t rst=%b\t a_i=%b\t out_rise=%b\t out_fall=%b",$time,clk,rst,a_i,out_rise,out_fall);
    $dumpfile("rise_fall_edge_dect.wavedump.vcd");
    $dumpvars(0, rise_fall_edge_dect_tb);
end

endmodule

//iverilog -g2012 -o rise_fall_edge_dect_wavedump.vvp rise_fall_edge_dect_tb.sv
//vvp rise_fall_edge_dect_wavedump.vvp

100_days_of_RTL/day_3_rise_fall_edge_dect/rise_fall_edge_dect.wavedump.vcd
$date
	Thu Sep 19 22:54:57 2024
$end
$version
	Icarus Verilog
$end
$timescale
	1s
$end
$scope module rise_fall_edge_dect_tb $end
$var wire 1 ! out_rise $end
$var wire 1 " out_fall $end
$var reg 1 # a_i $end
$var reg 1 $ clk $end
$var reg 1 % rst $end
$scope module uut $end
$var wire 1 # a_i $end
$var wire 1 $ clk $end
$var wire 1 % rst $end
$var reg 1 " out_fall $end
$var reg 1 ! out_rise $end
$var reg 1 & prev_a_i $end
$upscope $end
$upscope $end
$enddefinitions $end
$comment Show the parameter values. $end
$dumpall
$end
#0
$dumpvars
0&
1%
0$
0#
0"
0!
$end
#5
1$
#10
0$
0%
#15
1$
#20
0$
1#
#25
1&
1!
1$
#30
0$
#35
0!
1$
#40
0$
0#
#45
0&
1"
1$
#50
0"
0&
0$
1%
1#
#55
1&
1$
#60
0$
0#
#65
0&
1$
#70
0$
1#
#75
1&
1$
#80
0$
#85
0&
1$
#90
0$
0%
0#
#95
1$
#100
0$
1#
#105
1!
1&
1$
#110
0$
0#
#115
0&
1"
0!
1$
#120
0$
1#
#125
0"
1!
1&
1$
#130
0$
#135
0!
1$
#140
0$
0#
#145
1"
0&
1$
#150
0$
1#
#155
1&
0"
1!
1$
#160
0$
0#
#165
1"
0!
0&
1$
#170
0$
#175
0"
1$
