100_days_of_RTL/day_4_alu/alu.sv
// Design and verify a 8-bit ALU which supports the following encoded operations:
/*
3'b000	ADD	-
3'b001	SUB	-
3'b010	SLL	Vector a should left shift using bits 2:0 of vector b
3'b011	LSR	Vector a should right shift using bits 2:0 of vector b
3'b100	AND	-
3'b101	OR	-
3'b110	XOR	-
3'b111	EQL	Output should be 1 when equal otherwise 0
*/

module alu (
    input logic [7:0]a,
    input logic [7:0]b,
    input logic [2:0]encode_op,

    output logic [7:0]alu_o
);

logic carry;

always@(*) begin //can't use always_comb 
    case(encode_op)
    3'b000: {carry, alu_o}= {1'b0, a} + {1'b0, b};
    //3'b000: alu_o = a+b;
    3'b001: alu_o = a-b;
    3'b010: alu_o = a[7:0]<<b[2:0];
    3'b011: alu_o = a[7:0]>>b[2:0];
    3'b100: alu_o = a&b;
    3'b101: alu_o = a|b;
    3'b110: alu_o = a^b;
    3'b111: alu_o = a == b;

    endcase
end


endmodule

100_days_of_RTL/day_4_alu/alu_tb.sv
`include "alu.sv"

module alu_tb;

logic [7:0]a; 
logic [7:0]b;
logic [2:0]encode_op; 
logic [7:0]alu_o;

alu uut(.*);

initial begin

     // Initialize inputs
    a = 8'h91;
    b = 8'h91;
    encode_op = 3'b000;

    #10;
    a=8'h1f;
    b=8'h11;
    encode_op=3'b001;
   

    #10;
    a=8'h11;
    b=8'h01;
    encode_op=3'b010;
    
    #10;
    a=8'h11;
    b=8'h01;
    encode_op=3'b011;

    #10;
    a=8'h1f;
    b=8'h11;
    encode_op=3'b100;

    #10;
    a=8'h1f;
    b=8'h11;
    encode_op=3'b101;

    #10;
    a=8'h1f;
    b=8'h11;
    encode_op=3'b110;

    #10;
    a=8'h1f;
    b=8'h1f;
    encode_op=3'b111;


   #20 $finish;
end

initial begin
    $monitor("time=%t\t a=%h\t b=%h\t encode_op=%b alu_o=%h\t",$time,a,b,encode_op,alu_o);
    $dumpfile("alu_wavedump.vcd");
    $dumpvars(0, alu_tb);
end

endmodule

100_days_of_RTL/day_4_alu/alu_wavedump.vcd
$date
	Fri Sep 20 16:48:23 2024
$end
$version
	Icarus Verilog
$end
$timescale
	1s
$end
$scope module alu_tb $end
$var wire 8 ! alu_o [7:0] $end
$var reg 8 " a [7:0] $end
$var reg 8 # b [7:0] $end
$var reg 3 $ encode_op [2:0] $end
$scope module uut $end
$var wire 8 % a [7:0] $end
$var wire 8 & b [7:0] $end
$var wire 3 ' encode_op [2:0] $end
$var reg 8 ( alu_o [7:0] $end
$var reg 1 ) carry $end
$upscope $end
$upscope $end
$enddefinitions $end
$comment Show the parameter values. $end
$dumpall
$end
#0
$dumpvars
1)
b100010 (
b0 '
b10010001 &
b10010001 %
b0 $
b10010001 #
b10010001 "
b100010 !
$end
#10
b1110 !
b1110 (
b1 $
b1 '
b10001 #
b10001 &
b11111 "
b11111 %
#20
b100010 !
b100010 (
b10 $
b10 '
b1 #
b1 &
b10001 "
b10001 %
#30
b1000 !
b1000 (
b11 $
b11 '
#40
b10001 !
b10001 (
b100 $
b100 '
b10001 #
b10001 &
b11111 "
b11111 %
#50
b11111 !
b11111 (
b101 $
b101 '
#60
b1110 !
b1110 (
b110 $
b110 '
#70
b1 !
b1 (
b111 $
b111 '
b11111 #
b11111 &
