100_days_of_RTL/day_1_mux_2_1/mux_2_1.sv
//2:1 mux 

module mux_2_1 (
    input logic [7:0] a_i,
    input logic [7:0] b_i,
    input logic sel,
    output logic [7:0] y
);

//if sel==0 y=b_i & if sel==1 y=a_i

assign y = sel ? a_i : b_i;

/*always_comb begin
case (sel)
    1'b0    : y=b_i;
    1'b1    : y=a_i; 
    default : y=1'bx; 
endcase
end*/

endmodule

100_days_of_RTL/day_1_mux_2_1/mux_2_1_tb.sv
`include "mux_2_1.sv"

module mux_2_1_tb;

logic [7:0]a_i;
logic [7:0]b_i;
logic sel;
logic [7:0]y_out;

mux_2_1 uut(.a_i(a_i),.b_i(b_i),.sel(sel),.y(y_out));


/*initial begin
    a_i=0;
    b_i=1;
    sel=1;
    #5;
    sel=0; 
end*/

initial begin
    a_i=8'h00;
    b_i=8'hFF;
    sel=0;
    #5;
    for(int i =0; i<=10; i++) begin
    a_i= $urandom_range(0,8'hFF);
    b_i= $urandom_range(0,8'hFF);
    sel=$random%2;
    #5;
    end
end

initial begin
    $monitor("time=%t\t a_i=%h\t b_i=%h\t sel=%h\t y_out=%h\t",$time,a_i,b_i,sel,y_out);
    $dumpfile("mux_2_1_wavedump.vcd");
    $dumpvars(0,mux_2_1_tb);
end
endmodule

//--command to compile in iverilog--//
//iverilog -g2012 -o mux_2_1.vvp mux_2_1_tb.sv

//--command to display output and wavedump--/
//vvp mux_2_1.vvp

100_days_of_RTL/day_1_mux_2_1/mux_2_1_wavedump.vcd
$date
	Mon Sep 16 17:15:59 2024
$end
$version
	Icarus Verilog
$end
$timescale
	1s
$end
$scope module mux_2_1_tb $end
$var wire 8 ! y_out [7:0] $end
$var reg 8 " a_i [7:0] $end
$var reg 8 # b_i [7:0] $end
$var reg 1 $ sel $end
$scope module uut $end
$var wire 8 % a_i [7:0] $end
$var wire 8 & b_i [7:0] $end
$var wire 1 $ sel $end
$var wire 8 ' y [7:0] $end
$upscope $end
$scope begin $ivl_for_loop0 $end
$var integer 32 ( i [31:0] $end
$upscope $end
$upscope $end
$enddefinitions $end
$comment Show the parameter values. $end
$dumpall
$end
#0
$dumpvars
b0 (
b11111111 '
b11111111 &
b0 %
0$
b11111111 #
b0 "
b11111111 !
$end
#5
b1000000 !
b1000000 '
b1000000 #
b1000000 &
b10010010 "
b10010010 %
#10
b100 !
b100 '
1$
b110001 #
b110001 &
b100 "
b100 %
b1 (
#15
b10000110 !
b10000110 '
b11000110 #
b11000110 &
b10000110 "
b10000110 %
b10 (
#20
b110010 !
b110010 '
b1001 #
b1001 &
b110010 "
b110010 %
b11 (
#25
b10000000 !
b10000000 '
b10000110 #
b10000110 &
b10000000 "
b10000000 %
b100 (
#30
b10111011 !
b10111011 '
b10011110 #
b10011110 &
b10111011 "
b10111011 %
b101 (
#35
b11110110 !
b11110110 '
b11000110 #
b11000110 &
b11110110 "
b11110110 %
b110 (
#40
b1100011 !
b1100011 '
0$
b1100011 #
b1100011 &
b11111100 "
b11111100 %
b111 (
#45
b1100010 !
b1100010 '
1$
b1010101 #
b1010101 &
b1100010 "
b1100010 %
b1000 (
#50
b11110010 !
b11110010 '
b111011 #
b111011 &
b11110010 "
b11110010 %
b1001 (
#55
b11000111 !
b11000111 '
0$
b11000111 #
b11000111 &
b1001 "
b1001 %
b1010 (
#60
b1011 (
